{
  "ticker": "AYI",
  "form": "10-Q",
  "filing_date": "2020-06-29",
  "num_subsections": 15,
  "total_tokens": 12020,
  "subsections": [
    {
      "name": "Introduction",
      "section": "mda",
      "text": "id=\"s9DE55873C8DD5350873F4A52959958F9\">\nTable of Contents\n\nItem 2.Management\u2019s Discussion and Analysis of Financial Condition and Results of Operations\n\nThe purpose of this discussion and analysis is to enhance the understanding and evaluation of the results of operations, financial position, cash flows, indebtedness, and other key financial information of Acuity Brands, Inc. (\u201cAcuity Brands\u201d) and its subsidiaries as of May\u00a031, 2020 and for the three and nine months ended May 31, 2020 and 2019 . The following discussion should be read in conjunction with the Consolidated Financial Statements and Notes to Consolidated Financial Statements included within this report. Also, please refer to Acuity Brands' Annual Report on Form 10-K for the fiscal year ended August\u00a031, 2019 , filed with the Securities and Exchange Commission (the \u201cSEC\u201d) on October\u00a029, 2019 (\u201cForm 10-K\u201d).",
      "token_estimate": 219
    },
    {
      "name": "Company",
      "section": "mda",
      "text": "Acuity Brands is the parent company of Acuity Brands Lighting, Inc. (\u201cABL\u201d) and other subsidiaries (Acuity Brands, ABL, and such other subsidiaries are collectively referred to herein as \u201cwe,\u201d \u201cour,\u201d \u201cus,\u201d \u201cthe Company,\u201d or similar references). Our principal office is located in Atlanta, Georgia.\nWe are a market-leading industrial technology company that develops, manufactures, and provides lighting and building management solutions and services for commercial, institutional, industrial, infrastructure, and residential applications throughout North America and select international markets. Our lighting and building management solutions include devices such as luminaires, lighting controls, controls for various building systems, power supplies, prismatic skylights, and drivers, as well as integrated systems designed to optimize energy efficiency and comfort for various indoor and outdoor applications. Additionally, we continue to expand our solutions portfolio, including software and services, to provide a host of other economic benefits resulting from data analytics that enables the Internet of Things (\u201cIoT\u201d), supports the advancement of smart buildings, and allows businesses to develop custom applications to scale their operations. As of May\u00a031, 2020 , we operate 20 manufacturing facilities and eight distribution facilities along with three warehouses to serve our extensive customer base.\nWe do not consider acquisitions a critical element of our strategy but seek opportunities to expand and enhance our portfolio of solutions, including the following transactions:\nOn September 17, 2019, using cash on hand and borrowings under available existing credit arrangements, we acquired all of the equity interests of\u00a0The Luminaires Group\u00a0(\u201cTLG\u201d), a leading provider of specification-grade luminaires for commercial, institutional, hospitality, and municipal markets, all of which complement our current and dynamic lighting portfolio. TLG\u2019s indoor and outdoor lighting fixtures are marketed to architects, landscape architects, interior designers, and engineers through five niche lighting brands:\u00a0A-light,\u00a0Cyclone,\u00a0Eureka,\u00a0Luminaire LED,\u00a0and\u00a0Luminis.\nOn November 25, 2019, using cash on hand, we acquired all of the equity interests of LocusLabs, Inc (\u201cLocusLabs\u201d). The LocusLabs software platform supports navigation applications used on mobile devices, web browsers, and digital displays in airports, event centers, multi-floor office buildings, and campuses.\nThe results of operations for the three and nine months ended May 31, 2020 and 2019 are not necessarily indicative of the results to be expected for the full fiscal year due primarily to continued uncertainty of general economic conditions that may impact our key end markets for the remainder of fiscal 2020 , seasonality, and the impact of any acquisitions, among other reasons. Additionally, we are uncertain of the future impact of the ongoing COVID-19 pandemic and of possible sustained deterioration in economic conditions to our sales channels, supply chain, manufacturing, and distribution as well as overall construction, renovation, and consumer spending.",
      "token_estimate": 787
    },
    {
      "name": "The COVID-19 Pandemic",
      "section": "mda",
      "text": "During March 2020, the World Health Organization declared the COVID-19 outbreak a pandemic. This pandemic has resulted in worldwide government restrictions on the movement of people, goods, and services resulting in increased volatility in and disruptions to global markets. However, our manufacturing operations are deemed essential and continue to operate. We remain committed to prioritizing the health and well-being of our associates and their families and ensuring that we operate effectively. We have implemented policies to screen associates, contractors, and vendors for COVID-19 symptoms upon entering our manufacturing and distribution and open office facilities in the United States, Mexico, and other locations as permitted by law. We have also implemented one-way traffic flows, additional cleaning requirements for common spaces, mandatory face coverings, hand sanitizer stations, social-distanced workspaces, and self-serve pay stations within our cafeterias to mitigate the spread of the virus. Additionally, we are requiring certain employees whose job functions can be performed remotely to work from home into the forseeable future.\n21\n\nTable of Contents\nDuring the third quarter of fiscal 2020, government-mandated and voluntary social distancing measures had an adverse impact on our results of operations. The pandemic has caused reduced construction and renovation spending during the quarter as well as a disruption in our supply chain for certain components, both of which negatively impacted our third quarter fiscal 2020 sales volumes. We also experienced a limited number of temporary facility shutdowns due to government-mandated closures as well as additional health and safety costs including expenditures for personal protection equipment and facility enhancements to maintain proper distancing guidelines issued by the Centers for Disease Control and Prevention. In response to our sales volume declines, we have taken actions to reduce costs, including the realignment of headcount with current volumes, a freeze on all non-essential employee travel, and other efforts to decrease discretionary spending.\nAlthough we have implemented significant measures to mitigate further spread of the virus, our employees, customers, suppliers, and contractors may continue to experience disruptions to business activities due to potential further government-mandated or voluntary shutdowns, general economic conditions, or other negative impacts of the COVID-19 pandemic. We are continuously monitoring the adverse effects of the pandemic and identifying steps to mitigate those effects. As the COVID-19 pandemic is continually evolving, we are uncertain of its ultimate duration and impact. See Part II, Item 1a. Risk Factors for fu rther details regarding the potential impacts of COVID-19 to our results of operations, financial position, and cash flows.",
      "token_estimate": 720
    },
    {
      "name": "Liquidity and Capital Resources",
      "section": "mda",
      "text": "Our principal sources of liquidity are operating cash flows generated primarily from our business operations, cash on hand, and various sources of borrowings. Our ability to generate sufficient cash flow from operations or to access certain capital markets, including banks, is necessary to fund our operations and capital expenditures, pay dividends, repurchase shares, meet obligations as they become due, and maintain compliance with covenants contained in our financing agreements.\nFor the first nine months of fiscal 2020 , we paid $38.3 million for property, plant, and equipment, primarily for tooling, equipment, new and enhanced information technology capabilities, and facility enhancements. We currently expect to invest between $10 million and $15 million on capital expenditures during the fourth quarter of fiscal 2020 .\nIn March 2018, the Board of Directors (the \u201cBoard\u201d) authorized the repurchase of up to six million shares of the Company's common stock. As of May\u00a031, 2020 , 1.45 million shares had been repurchased under this authorization. No shares were repurchased in fiscal 2020. We expect to repurchase the remaining shares available for repurchase on an opportunistic basis subject to various factors including stock price, Company performance, market conditions, and other possible uses of cash.\nOur short-term cash needs are expected to include funding operations as currently planned; making capital investments as currently anticipated; paying quarterly stockholder dividends as currently anticipated; paying principal and interest on debt as currently scheduled, including our borrowings under our unsecured delayed draw term loan facility (the \u201cTerm Loan Facility\u201d); making required contributions to our employee benefit plans; funding possible acquisitions; and potentially repurchasing shares of our outstanding common stock. We believe that we will be able to meet our liquidity needs over the next 12 months based on our cash on hand, current projections of cash flow from operations, and borrowing availability under financing arrangements. Additionally, we believe that our cash flows from operations and sources of funding, including, but not limited to, future borrowings and capacity, will sufficiently support our long-term liquidity needs. However, as the impact of the COVID-19 pandemic on the economy and our operations evolves, we will continue to assess our liquidity needs. A continued worldwide disruption could materially affect our future access to our sources of liquidity, particularly our cash flows from operations, financial condition, capitalization, and capital investments. In the event of a sustained market deterioration, we may need additional liquidity, which would require us to evaluate available alternatives and take appropriate actions.",
      "token_estimate": 700
    },
    {
      "name": "Cash Flow",
      "section": "mda",
      "text": "We use available cash and cash flows from operations, borrowings on credit arrangements, and proceeds from the exercise of stock options to fund operations, capital expenditures, and acquisitions if any; to repurchase Company stock; and to pay dividends.\nOur cash position at May\u00a031, 2020 was $520.6 million , an increase of $59.6 million from August\u00a031, 2019 . During the nine months ended May 31, 2020 , we generated net cash flows from operations of $378.3 million . Cash generated from operating activities, cash on-hand, and additional long-term debt borrowings were used during the nine months ended May 31, 2020 primarily to repay long term debt obligations due of $350.7 million , to fund acquisitions of $303.0 million , to fund capital expenditures of $38.3 million , to pay dividends to stockholders of $15.6 million , and to pay\n22\n\nTable of Contents\nwithholding taxes on the net settlement of equity awards of $5.1 million .\nWe generated $378.3 million of cash flows from operating activities during the nine months ended May\u00a031, 2020 compared with $312.0 million in the prior-year period, an increase of $66.3 million , due primarily to lower working capital requirements, partially offset by lower net income.\nWe believe that investing in assets and programs that will over time increase the overall return on our invested capital is a key factor in driving stockholder value. We paid $38.3 million and $39.8 million during the first nine months of fiscal 2020 and 2019 , respectively, for property, plant, and equipment, primarily related to investments in tooling, equipment, new and enhanced information technology capabilities, and facility enhancements.",
      "token_estimate": 418
    },
    {
      "name": "Capitalization",
      "section": "mda",
      "text": "As of May\u00a031, 2020 , our capital structure was comprised principally of borrowings on the Term Loan Facility and equity of our stockholders. Total debt outstanding was $403.6 million at May\u00a031, 2020 and consisted primarily of variable-rate obligations. At August\u00a031, 2019 , total debt outstanding was $356.6 million and consisted primarily of fixed-rate obligations.\nOn June\u00a029, 2018 , we entered into a credit agreement (\u201cCredit Agreement\u201d) with a syndicate of banks that provides us with a $400.0 million five-year unsecured revolving credit facility (\u201cRevolving Credit Facility\u201d) and a $400.0 million Term Loan Facility. We had no borrowings outstanding under the Revolving Credit Facility as of May\u00a031, 2020 or August\u00a031, 2019 . We had $397.5 million in borrowings outstanding under the Term Loan Facility as of May\u00a031, 2020 and no borrowings outstanding under the Term Loan Facility as of August\u00a031, 2019 . Based on the repayment schedule, $380.0 million of the borrowings under the Term Loan Facility are reflected within Long-term debt on the Consolidated Balance Sheets as of May\u00a031, 2020 .\nIn December 2019, we borrowed the full $400.0 million available under our Term Loan Facility. The proceeds were primarily used to repay the $350.0 million of senior unsecured notes, which matured on December 15, 2019, and the related accrued interest in full. Borrowings under the Term Loan Facility amortize in equal quarterly installments per year as described in the Debt and Lines of Credit footnote of the Notes to Consolidated Financial Statements . Any remaining borrowings under the Term Loan Facility are due and payable in full on June 29, 2023. Additionally, see the Debt and Lines of Credit footnote for interest rates related to the Term Loan Facility. There have been no other material changes outside of the ordinary course of business in our contractual obligations since August\u00a031, 2019 .\nWe were in compliance with all financial covenants under the Credit Agreement as of May\u00a031, 2020 . At May\u00a031, 2020 , we had additional borrowing capacity under the Credit Agreement of $396.2 million under the most restrictive covenant in effect at the time, which represents the full amount of the Revolving Credit Facility less the outstanding letters of credit of $3.8 million issued under the Revolving Credit Facility. As of May\u00a031, 2020 , we had outstanding letters of credit totaling $8.1 million , primarily for securing collateral requirements under our casualty insurance programs and for providing credit support for our industrial revenue bond, which includes the $3.8 million issued under the Revolving Credit Facility. See the Debt and Lines of Credit footnote of the Notes to Consolidated Financial Statements for more information.\nDuring the first nine months of fiscal 2020 , our consolidated stockholders\u2019 equity increased $176.8 million to $2.1 billion at May\u00a031, 2020 , from $1.9 billion at August\u00a031, 2019 . The increase was due primarily to comprehensive income, partially offset by the payment of dividends. Our debt to total capitalization ratio (calculated by dividing total debt by the sum of total debt and total stockholders\u2019 equity) was 16.1% and 15.7% at May\u00a031, 2020 and August\u00a031, 2019 , respectively. The ratio of debt, net of cash, to total capitalization, net of cash, was (5.9)% and (5.8)% at May\u00a031, 2020 and August\u00a031, 2019 , respectively.",
      "token_estimate": 845
    },
    {
      "name": "Dividends",
      "section": "mda",
      "text": "We paid dividends on our common stock of $15.6 million ( $0.39 per share) during the nine months ended May\u00a031, 2020 and 2019 . All decisions regarding the declaration and payment of dividends are at the discretion of the Board and are evaluated regularly in light of our financial condition, earnings, growth prospects, funding requirements, applicable law, and any other factors the Board deems relevant.\n23\n\nTable of Contents",
      "token_estimate": 106
    },
    {
      "name": "Third Quarter of Fiscal 2020 Compared with Third Quarter of Fiscal 2019",
      "section": "mda",
      "text": "The following table sets forth information comparing the components of net income for the three months ended May\u00a031, 2020 and 2019 (in millions except per share data):\nThree Months Ended \u00a0 \u00a0 \u00a0 \u00a0 \u00a0 May\u00a031, 2020 \u00a0 May\u00a031, 2019 \u00a0 Increase (Decrease) \u00a0 Percent Change Net sales $ 776.2 \u00a0 $ 947.6 \u00a0 $ (171.4 ) \u00a0 (18.1 )% Cost of products sold 448.6 \u00a0 564.0 \u00a0 (115.4 ) \u00a0 (20.5 )% Gross profit 327.6 \u00a0 383.6 \u00a0 (56.0 ) \u00a0 (14.6 )% Percent of net sales 42.2 % \u00a0 40.5 % \u00a0 170 bps \u00a0 Selling, distribution, and administrative expenses 241.3 \u00a0 263.4 \u00a0 (22.1 ) \u00a0 (8.4 )% Special charges 3.3 \u00a0 (0.1 ) \u00a0 3.4 \u00a0 NM Operating profit 83.0 \u00a0 120.3 \u00a0 (37.3 ) \u00a0 (31.0 )% Percent of net sales 10.7 % \u00a0 12.7 % \u00a0 (200 ) bps \u00a0 Other expense: \u00a0 \u00a0 \u00a0 \u00a0 \u00a0 \u00a0 \u00a0 Interest expense, net 5.4 \u00a0 8.3 \u00a0 (2.9 ) \u00a0 (34.9 )% Miscellaneous (income) expense, net (0.9 ) \u00a0 0.2 \u00a0 (1.1 ) \u00a0 NM Total other expense 4.5 \u00a0 8.5 \u00a0 (4.0 ) \u00a0 (47.1 )% Income before income taxes 78.5 \u00a0 111.8 \u00a0 (33.3 ) \u00a0 (29.8 )% Percent of net sales 10.1 % \u00a0 11.8 % \u00a0 (170 ) bps Income tax expense 18.1 \u00a0 23.4 \u00a0 (5.3 ) \u00a0 (22.6 )% Effective tax rate 23.1 % \u00a0 20.9 % \u00a0 \u00a0 \u00a0 \u00a0 Net income $ 60.4 \u00a0 $ 88.4 \u00a0 $ (28.0 ) \u00a0 (31.7 )% Diluted earnings per share $ 1.52 \u00a0 $ 2.22 \u00a0 $ (0.70 ) \u00a0 (31.5 )% NM - not meaningful\nNet sales were $776.2 million for the three months ended May 31, 2020 compared with $947.6 million reported for the three months ended May 31, 2019 , a decrease of $171.4 million , or 18.1% . For the three months ended May 31, 2020 , we reported net income of $60.4 million , a decrease of $28.0 million , or 31.7% , compared with $88.4 million for the three months ended May 31, 2019 . For the third quarter of fiscal 2020 , diluted earnings per share decreased 31.5% to $1.52 compared with $2.22 reported in the year-ago period.\nThe following table reconciles certain U.S. generally accepted accounting principles (\u201cU.S. GAAP\u201d) financial measures to the corresponding non-U.S. GAAP measures referred to in the discussion of our results of operations, which exclude the impact of amortization of acquired intangible assets, share-based payment expense, and special charges associated primarily with continued efforts to streamline the organization and integrate recent acquisitions. Although the impacts of some of these items have been recognized in prior periods and could recur in future periods, we typically exclude these charges during internal reviews of performance and use these non-U.S. GAAP measures for baseline comparative operational analysis, decision making, and other activities. These non-U.S. GAAP financial measures, including adjusted selling, distribution, and administrative (\u201cSD&A\u201d) expenses and adjusted SD&A expenses as a percent of net sales, adjusted operating profit and margin, adjusted net income, and adjusted diluted earnings per share, are provided to enhance the user\u2019s overall understanding of our current financial performance. Specifically, we believe these non-U.S. GAAP measures provide greater comparability and enhanced visibility into our results of operations. The non-U.S. GAAP financial measures should be considered in addition to, and not as a substitute for or superior to, results prepared in accordance with U.S. GAAP.\n24\n\nTable of Contents\n(In millions, except per share data) Three Months Ended \u00a0 \u00a0 \u00a0 \u00a0 \u00a0 \u00a0 May\u00a031, 2020 \u00a0 \u00a0 \u00a0 May\u00a031, 2019 \u00a0 \u00a0 \u00a0 Increase (Decrease) Percent Change Selling, distribution, and administrative expenses $ 241.3 \u00a0 \u00a0 \u00a0 $ 263.4 \u00a0 \u00a0 \u00a0 $ (22.1 ) (8.4 )% Percent of net sales \u00a0 \u00a0 31.1 % \u00a0 \u00a0 \u00a0 27.8 % \u00a0 330 bps Less: Amortization of acquired intangible assets (10.8 ) \u00a0 \u00a0 \u00a0 (7.7 ) \u00a0 \u00a0 \u00a0 \u00a0 \u00a0 Less: Share-based payment expense (7.8 ) \u00a0 \u00a0 \u00a0 (7.6 ) \u00a0 \u00a0 \u00a0 \u00a0 \u00a0 Adjusted selling, distribution, and administrative expenses $ 222.7 \u00a0 \u00a0 \u00a0 $ 248.1 \u00a0 \u00a0 \u00a0 $ (25.4 ) (10.2 )% Percent of net sales \u00a0 \u00a0 28.7 % \u00a0 \u00a0 \u00a0 26.2 % \u00a0 250 bps \u00a0 \u00a0 \u00a0 \u00a0 \u00a0 \u00a0 \u00a0 \u00a0 \u00a0 \u00a0 \u00a0 Operating profit $ 83.0 \u00a0 \u00a0 \u00a0 $ 120.3 \u00a0 \u00a0 \u00a0 $ (37.3 ) (31.0 )% Percent of net sales \u00a0 \u00a0 10.7 % \u00a0 \u00a0 \u00a0 12.7 % \u00a0 (200 ) bps Add-back: Amortization of acquired intangible assets 10.8 \u00a0 \u00a0 \u00a0 7.7 \u00a0 \u00a0 \u00a0 \u00a0 \u00a0 Add-back: Share-based payment expense 7.8 \u00a0 \u00a0 \u00a0 7.6 \u00a0 \u00a0 \u00a0 \u00a0 \u00a0 Add-back: Special charges 3.3 \u00a0 \u00a0 \u00a0 (0.1 ) \u00a0 \u00a0 \u00a0 \u00a0 \u00a0 Adjusted operating profit $ 104.9 \u00a0 \u00a0 \u00a0 $ 135.5 \u00a0 \u00a0 \u00a0 $ (30.6 ) (22.6 )% Percent of net sales \u00a0 \u00a0 13.5 % \u00a0 \u00a0 \u00a0 14.3 % \u00a0 (80 ) bps \u00a0 \u00a0 \u00a0 \u00a0 \u00a0 \u00a0 \u00a0 \u00a0 \u00a0 \u00a0 \u00a0 Net income $ 60.4 \u00a0 \u00a0 \u00a0 $ 88.4 \u00a0 \u00a0 \u00a0 $ (28.0 ) (31.7 )% Add-back: Amortization of acquired intangible assets 10.8 \u00a0 \u00a0 \u00a0 7.7 \u00a0 \u00a0 \u00a0 \u00a0 \u00a0 Add-back: Share-based payment expense 7.8 \u00a0 \u00a0 \u00a0 7.6 \u00a0 \u00a0 \u00a0 \u00a0 \u00a0 Add-back: Special charges 3.3 \u00a0 \u00a0 \u00a0 (0.1 ) \u00a0 \u00a0 \u00a0 \u00a0 \u00a0 Total pre-tax adjustments to net income 21.9 \u00a0 \u00a0 \u00a0 15.2 \u00a0 \u00a0 \u00a0 \u00a0 \u00a0 Income tax effects (5.1 ) \u00a0 \u00a0 \u00a0 (3.0 ) \u00a0 \u00a0 \u00a0 \u00a0 \u00a0 Adjusted net income $ 77.2 \u00a0 \u00a0 \u00a0 $ 100.6 \u00a0 \u00a0 \u00a0 $ (23.4 ) (23.3 )% \u00a0 \u00a0 \u00a0 \u00a0 \u00a0 \u00a0 \u00a0 \u00a0 \u00a0 \u00a0 \u00a0 Diluted earnings per share $ 1.52 \u00a0 \u00a0 \u00a0 $ 2.22 \u00a0 \u00a0 \u00a0 $ (0.70 ) (31.5 )% Adjusted diluted earnings per share $ 1.94 \u00a0 \u00a0 \u00a0 $ 2.53 \u00a0 \u00a0 \u00a0 $ (0.59 ) (23.3 )%\nNet Sales\nNet sales for the three months ended May 31, 2020 decreased 18.1% compared with the prior-year period due primarily to a 20% decrease in sales volumes, partially offset by a contribution from acquired businesses of approximately 2% . Fiscal 2020 third quarter sales volumes decreased compared with the prior year due primarily to the negative impacts of the COVID-19 pandemic. The change in product prices and mix of products sold (\u201cprice/mix\u201d) was flat year over year as a favorable shift in sales channel mix was offset by overall lower pricing. Due to the changing dynamics of our product portfolio, it is not possible to precisely quantify or differentiate the individual components of volume, price, and mix.\nGross Profit\nGross profit for the third quarter of fiscal 2020 decreased $56.0 million , or 14.6% , to $327.6 million compared with $383.6 million in the prior-year period, due primarily to lower sales volumes as a result of the COVID-19 pandemic as described above, partially offset by lower costs for certain inputs as well as the contribution from acquisitions. Tariffs also continue to impact cost of goods sold and are expected to continue. Gross profit margin increased 170 basis points to 42.2% for the three months ended May 31, 2020 compared with 40.5% in the prior-year period. The improvement in gross profit margin was due primarily to lower costs for certain inputs, contributions from acquisitions, and favorable sales channel mix partially offset by lower average selling prices.\nOperating Profit\nSD&A expenses for the three months ended May 31, 2020 were $241.3 million compared with $263.4 million in the prior-year period, a decrease of $22.1 million , or 8.4% . The decrease in SD&A expenses was due primarily to decreased freight and commissions associated with lower sales volumes, travel expenses, sales and marketing expenses, and salaried employee costs due in part to the COVID-19 pandemic. These declines were partially offset by additional costs from recent acquisitions, including additional amortization of acquired intangibles, and employee costs. SD&A expenses for the third quarter of fiscal 2020 were 31.1% of net sales compared with 27.8% for the prior-year period.\n25\n\nTable of Contents\nThis increase was due primarily to higher overall commission rates associated with channel mix and acquisitions, increased amortization of acquired intangibles, and higher employee costs from acquisitions. Adjusted SD&A expenses for the three months ended May 31, 2020 were $222.7 million ( 28.7% of net sales) compared with $248.1 million ( 26.2% of net sales) in the prior-year period.\nWe recognized pre-tax special charges of $3.3 million during the third quarter of fiscal 2020 compared with pre-tax special charge credits of $0.1 million recorded during the third quarter of fiscal 2019 . Further details regarding our special charges are included in the Special Charges footnote of the Notes to Consolidated Financial Statements .\nOperating profit for the third quarter of fiscal 2020 was $83.0 million ( 10.7% of net sales) compared with $120.3 million ( 12.7% of net sales) for the prior-year period, a decrease of $37.3 million , or 31.0% . The decrease in operating profit was due to lower gross profit and increased special charges, partially offset by lower SD&A expenses. Adjusted operating profit decreased $30.6 million , or 22.6% , to $104.9 million for the third quarter of fiscal 2020 compared with $135.5 million for the third quarter of fiscal 2019 . Adjusted operating profit margin decreased to 13.5% for the third quarter of fiscal 2020 compared with 14.3% for the year-ago period.\nOther Expense\nOther expense consists of net interest expense and net miscellaneous (income) expense, which includes non-service related components of net periodic pension cost, gains and losses associated with foreign currency-related transactions, and non-operating gains and losses. Interest expense, net, was $5.4 million and $ 8.3 million for the three months ended May 31, 2020 and 2019 , respectively. The decrease in interest expense was due primarily to the interest savings associated with refinancing the previously outstanding 6% senior unsecured notes with funds under the Term Loan Facility, which are subject to lower short-term borrowing rates. We reported net miscellaneous income of $0.9 million and net miscellaneous expense $0.2 million for the three months ended May 31, 2020 and 2019 , respectively.\nIncome Taxes and Net Income\nOur effective income tax rate was 23.1% and 20.9% for the three months ended May 31, 2020 and 2019 , respectively. The increase in the current fiscal tax rate was due primarily to the recognition in fiscal 2019 of certain research and development cost tax credits, including claims for prior periods, that did not recur in the current fiscal year. We currently estimate that our blended consolidated effective income tax rate, before any discrete items, will be approximately 23% for fiscal 2020 , assuming the rates in our taxing jurisdictions remain generally consistent throughout the year.\nNet income for the third quarter of fiscal 2020 decreased $28.0 million , or 31.7% , to $60.4 million from $88.4 million reported for the prior-year period. The decrease in net income resulted primarily from a decreased operating profit compared to the prior-year period partially offset by lower interest expense and income tax expense. Diluted earnings per share for the three months ended May 31, 2020 decreased $0.70 to $1.52 compared with diluted earnings per share of $2.22 for the prior-year period. This decrease reflects lower net income. Adjusted net income for the third quarter of fiscal 2020 was $77.2 million , compared with $100.6 million in the prior-year period, a decrease of $23.4 million , or 23.3% . Adjusted diluted earnings per share for the three months ended May 31, 2020 decreased $0.59 , or 23.3% , to $1.94 compared with $2.53 for the prior-year period.\n26\n\nTable of Contents",
      "token_estimate": 2729
    },
    {
      "name": "First Nine Months of Fiscal 2020 Compared with First Nine Months of Fiscal 2019",
      "section": "mda",
      "text": "The following table sets forth information comparing the components of net income for the nine months ended May\u00a031, 2020 and 2019 (in millions except per share data):\nNine Months Ended \u00a0 \u00a0 \u00a0 \u00a0 \u00a0 May\u00a031, 2020 May\u00a031, 2019 \u00a0 Increase (Decrease) \u00a0 Percent Change Net sales $ 2,435.1 \u00a0 $ 2,734.6 \u00a0 $ (299.5 ) \u00a0 (11.0 )% Cost of products sold 1,407.8 \u00a0 1,649.6 \u00a0 (241.8 ) \u00a0 (14.7 )% Gross profit 1,027.3 \u00a0 1,085.0 \u00a0 (57.7 ) \u00a0 (5.3 )% Percent of net sales 42.2 % \u00a0 39.7 % \u00a0 250 bps \u00a0 Selling, distribution, and administrative expenses 767.5 \u00a0 751.1 \u00a0 16.4 \u00a0 2.2 \u00a0% Special charges 11.8 \u00a0 1.3 \u00a0 10.5 \u00a0 NM Operating profit 248.0 \u00a0 332.6 \u00a0 (84.6 ) \u00a0 (25.4 )% Percent of net sales 10.2 % \u00a0 12.2 % \u00a0 (200 ) bps \u00a0 Other expense: \u00a0 \u00a0 \u00a0 \u00a0 \u00a0 \u00a0 \u00a0 Interest expense, net 19.4 \u00a0 25.6 \u00a0 (6.2 ) \u00a0 (24.2 )% Miscellaneous expense, net 1.5 \u00a0 2.6 \u00a0 (1.1 ) \u00a0 (42.3 )% Total other expense 20.9 \u00a0 28.2 \u00a0 (7.3 ) \u00a0 (25.9 )% Income before income taxes 227.1 \u00a0 304.4 \u00a0 (77.3 ) \u00a0 (25.4 )% Percent of net sales 9.3 % 11.1 % \u00a0 (180 ) bps Income tax expense 52.5 \u00a0 70.1 \u00a0 (17.6 ) \u00a0 (25.1 )% Effective tax rate 23.1 % \u00a0 23.0 % \u00a0 \u00a0 \u00a0 \u00a0 Net income $ 174.6 \u00a0 $ 234.3 \u00a0 $ (59.7 ) \u00a0 (25.5 )% Diluted earnings per share $ 4.40 \u00a0 $ 5.87 \u00a0 $ (1.47 ) \u00a0 (25.0 )% NM - not meaningful\nNet sales were $2.4 billion for the nine months ended May 31, 2020 compared with $2.7 billion reported for the nine months ended May 31, 2019 , a decrease of $299.5 million , or 11.0% . For the nine months ended May 31, 2020 , we reported net income of $174.6 million , a decrease of $59.7 million , or 25.5% , compared with $234.3 million for the nine months ended May 31, 2019 . For the first nine months of fiscal 2020 , diluted earnings per share decreased 25.0% to $4.40 compared with $5.87 reported in the year-ago period.\nThe following table reconciles certain U.S. GAAP financial measures to the corresponding non-U.S. GAAP measures referred to in the discussion of our results of operations, which exclude the impact of manufacturing inefficiencies, acquisition-related items, amortization of acquired intangible assets, share-based payment expense, and special charges associated primarily with continued efforts to streamline the organization. These non-U.S. GAAP financial measures, including adjusted gross profit and margin, adjusted SD&A expenses and adjusted SD&A expenses as a percent of net sales, adjusted operating profit and margin, adjusted net income, and adjusted diluted earnings per share, are provided to enhance the user\u2019s overall understanding of our current financial performance. Specifically, we believe these non-U.S. GAAP measures provide greater comparability and enhanced visibility into our results of operations. The non-U.S. GAAP financial measures should be considered in addition to, and not as a substitute for or superior to, results prepared in accordance with U.S. GAAP.\n27\n\nTable of Contents\n(In millions, except per share data) Nine Months Ended \u00a0 \u00a0 \u00a0 \u00a0 \u00a0 \u00a0 May\u00a031, 2020 \u00a0 \u00a0 \u00a0 May\u00a031, 2019 \u00a0 \u00a0 \u00a0 Increase (Decrease) Percent Change Gross profit $ 1,027.3 \u00a0 \u00a0 \u00a0 $ 1,085.0 \u00a0 \u00a0 \u00a0 $ (57.7 ) (5.3 )% Percent of net sales \u00a0 \u00a0 42.2 % \u00a0 \u00a0 \u00a0 39.7 % \u00a0 250 bps Add-back: Manufacturing inefficiencies (1) \u2014 \u00a0 \u00a0 \u00a0 0.9 \u00a0 \u00a0 \u00a0 \u00a0 \u00a0 Add-back: Acquisition-related items (2) 1.2 \u00a0 \u00a0 \u00a0 1.2 \u00a0 \u00a0 \u00a0 \u00a0 \u00a0 Adjusted gross profit $ 1,028.5 \u00a0 \u00a0 $ 1,087.1 \u00a0 \u00a0 \u00a0 $ (58.6 ) (5.4 )% Percent of net sales \u00a0 \u00a0 42.2 % \u00a0 \u00a0 \u00a0 39.8 % \u00a0 240 bps \u00a0 \u00a0 \u00a0 \u00a0 \u00a0 \u00a0 \u00a0 \u00a0 \u00a0 \u00a0 \u00a0 Selling, distribution, and administrative expenses $ 767.5 \u00a0 \u00a0 \u00a0 $ 751.1 \u00a0 \u00a0 \u00a0 $ 16.4 2.2 \u00a0% Percent of net sales \u00a0 \u00a0 31.5 % \u00a0 \u00a0 \u00a0 27.5 % \u00a0 400 bps Less: Amortization of acquired intangible assets (30.8 ) \u00a0 \u00a0 \u00a0 (23.1 ) \u00a0 \u00a0 \u00a0 \u00a0 \u00a0 Less: Share-based payment expense (32.5 ) \u00a0 \u00a0 \u00a0 (22.9 ) \u00a0 \u00a0 \u00a0 \u00a0 \u00a0 Less: Acquisition-related items (2) (1.3 ) \u00a0 \u00a0 \u00a0 \u2014 \u00a0 \u00a0 \u00a0 \u00a0 \u00a0 Adjusted selling, distribution, and administrative expenses $ 702.9 \u00a0 \u00a0 \u00a0 $ 705.1 \u00a0 \u00a0 \u00a0 $ (2.2 ) (0.3 )% Percent of net sales \u00a0 \u00a0 28.9 % \u00a0 \u00a0 \u00a0 25.8 % \u00a0 310 bps \u00a0 \u00a0 \u00a0 \u00a0 \u00a0 \u00a0 \u00a0 \u00a0 \u00a0 \u00a0 \u00a0 Operating profit $ 248.0 \u00a0 \u00a0 \u00a0 $ 332.6 \u00a0 \u00a0 \u00a0 $ (84.6 ) (25.4 )% Percent of net sales \u00a0 \u00a0 10.2 % \u00a0 \u00a0 \u00a0 12.2 % \u00a0 (200 ) bps Add-back: Amortization of acquired intangible assets 30.8 \u00a0 \u00a0 \u00a0 23.1 \u00a0 \u00a0 \u00a0 \u00a0 \u00a0 Add-back: Share-based payment expense 32.5 \u00a0 \u00a0 \u00a0 22.9 \u00a0 \u00a0 \u00a0 \u00a0 \u00a0 Add-back: Manufacturing inefficiencies (1) \u2014 \u00a0 \u00a0 \u00a0 0.9 \u00a0 \u00a0 \u00a0 \u00a0 \u00a0 Add-back: Acquisition-related items (2) 2.5 \u00a0 \u00a0 \u00a0 1.2 \u00a0 \u00a0 \u00a0 \u00a0 \u00a0 Add-back: Special charges 11.8 \u00a0 \u00a0 \u00a0 1.3 \u00a0 \u00a0 \u00a0 \u00a0 \u00a0 Adjusted operating profit $ 325.6 \u00a0 \u00a0 \u00a0 $ 382.0 \u00a0 \u00a0 \u00a0 $ (56.4 ) (14.8 )% Percent of net sales \u00a0 \u00a0 13.4 % \u00a0 \u00a0 \u00a0 14.0 % \u00a0 (60 ) bps \u00a0 \u00a0 \u00a0 \u00a0 \u00a0 \u00a0 \u00a0 \u00a0 \u00a0 \u00a0 \u00a0 Net income $ 174.6 \u00a0 \u00a0 \u00a0 $ 234.3 \u00a0 \u00a0 \u00a0 $ (59.7 ) (25.5 )% Add-back: Amortization of acquired intangible assets 30.8 \u00a0 \u00a0 \u00a0 23.1 \u00a0 \u00a0 \u00a0 \u00a0 \u00a0 Add-back: Share-based payment expense 32.5 \u00a0 \u00a0 \u00a0 22.9 \u00a0 \u00a0 \u00a0 \u00a0 \u00a0 Add-back: Manufacturing inefficiencies (1) \u2014 \u00a0 \u00a0 \u00a0 0.9 \u00a0 \u00a0 \u00a0 \u00a0 \u00a0 Add-back: Acquisition-related items (2) 2.5 \u00a0 \u00a0 \u00a0 1.2 \u00a0 \u00a0 \u00a0 \u00a0 \u00a0 Add-back: Special charges 11.8 \u00a0 \u00a0 \u00a0 1.3 \u00a0 \u00a0 \u00a0 \u00a0 \u00a0 Total pre-tax adjustments to net income 77.6 \u00a0 \u00a0 49.4 \u00a0 \u00a0 \u00a0 \u00a0 \u00a0 Income tax effect (17.7 ) \u00a0 \u00a0 \u00a0 (11.3 ) \u00a0 \u00a0 \u00a0 \u00a0 \u00a0 Adjusted net income $ 234.5 \u00a0 \u00a0 \u00a0 $ 272.4 \u00a0 \u00a0 \u00a0 $ (37.9 ) (13.9 )% \u00a0 \u00a0 \u00a0 \u00a0 \u00a0 \u00a0 \u00a0 \u00a0 \u00a0 \u00a0 Diluted earnings per share $ 4.40 \u00a0 \u00a0 \u00a0 $ 5.87 \u00a0 \u00a0 \u00a0 $ (1.47 ) (25.0 )% Adjusted diluted earnings per share $ 5.91 \u00a0 \u00a0 \u00a0 $ 6.83 \u00a0 \u00a0 \u00a0 $ (0.92 ) (13.5 )%\n______________________________\n(1) Incremental costs incurred due to manufacturing inefficiencies directly related to the closure of a facility.\n(2) Acquisition-related items include profit in inventory and professional fees.\nNet Sales\nNet sales for the nine months ended May 31, 2020 decreased $299.5 million , or 11.0% , compared with the prior-year period due primarily to a decrease in sales volume of approximately 14% , partially offset by a contribution from acquired businesses of approximately 2% as well as a net favorable change in price/mix of 1% .\u00a0Fiscal 2020 sales volumes decreased compared with the prior year due primarily to the negative impacts of the COVID-19 pandemic, and to a lesser extent the elimination of certain products in our portfolio negatively impacted by the increases in tariffs sold primarily through the retail sales channel that did not meet our return objectives. Price/mix was primarily impacted by\n28\n\nTable of Contents\na favorable shift in sales channel mix. Due to the changing dynamics of our product portfolio, it is not possible to precisely quantify or differentiate the individual components of volume, price, and mix.\nGross Profit\nGross profit for the first nine months of fiscal 2020 decreased $57.7 million compared to the prior-year period, while gross profit margin increased to 42.2% for the nine months ended May 31, 2020 compared with 39.7% in the prior-year period. The improvement in gross profit margin was due primarily to favorable sales channel mix, lower costs for certain inputs, and contribution from acquisitions, partially offset by lower net sales volume. Additionally, tariffs continued to have an impact on cost of goods sold. Adjusted gross profit for the nine months ended May 31, 2020 was $1.0 billion ( 42.2% of net sales) compared with $1.1 billion ( 39.8% of net sales) in the prior-year period.\nOperating Profit\nSD&A expenses for the nine months ended May 31, 2020 were $767.5 million compared with $751.1 million in the prior-year period, an increase of $16.4 million , or 2.2% . The increase in SD&A expenses was due primarily to higher share-based payment expense, the addition of acquisitions, including employee costs and amortization of acquired intangibles, and higher professional fees. Share-based payment expense increased due to changes made to the equity incentive program as part of the Company\u2019s comprehensive review of its compensation programs, which resulted in the acceleration of share-based payment expense in the first quarter of fiscal\u00a02020.\nSD&A expenses for the first nine months of fiscal 2020 were 31.5% of net sales compared with 27.5% for the prior-year period. Adjusted SD&A expenses for the nine months ended May 31, 2020 were $702.9 million ( 28.9% of net sales) compared with $705.1 million ( 25.8% of net sales) in the prior-year period.\nWe recognized pre-tax special charges of $11.8 million during the first nine months of fiscal 2020 , compared with pre-tax special charges of $1.3 million during the first nine months of fiscal 2019 . Further details regarding our special charges are included in the Special Charge footnote of the Notes to Consolidated Financial Statements .\nOperating profit for the first nine months of fiscal 2020 was $248.0 million ( 10.2% of net sales) compared with $332.6 million ( 12.2% of net sales) for the prior-year period, a decrease of $84.6 million , or 25.4% . The decrease in operating profit was due to lower gross profit, an increase in SD&A expenses, and higher pre-tax special charges. Adjusted operating profit decreased by $56.4 million , or 14.8% , to $325.6 million for the first nine months of fiscal 2020 compared with $382.0 million for the first nine months of fiscal 2019 . Adjusted operating profit margin for the first nine months of fiscal 2020 decreased 60 basis points to 13.4% compared with 14.0% in the year-ago period.\nOther Expense\nOther expense consists of net interest expense and net miscellaneous expense, which includes non-service related components of net periodic pension cost, gains and losses associated with foreign currency-related transactions, and non-operating gains and losses. Interest expense, net, was $19.4 million and $25.6 million for the nine months ended May 31, 2020 and 2019 , respectively. The decrease in interest expense was due primarily to the interest savings associated with refinancing the previously outstanding 6% senior unsecured notes with funds under the Term Loan Facility, which are subject to lower short-term borrowing rates. We reported net miscellaneous expense of $1.5 million and $2.6 million for the nine months ended May 31, 2020 and 2019 , respectively.\nIncome Taxes and Net Income\nOur effective income tax rate was 23.1% and 23.0% for the nine months ended May 31, 2020 and 2019 , respectively.\nNet income for the first nine months of fiscal 2020 decreased $59.7 million , or 25.5% , to $174.6 million from $234.3 million reported for the prior-year period. The decrease in net income resulted primarily from a decreased operating profit compared to the prior-year period partially offset by lower interest expense and income tax expense. Diluted earnings per share for the nine months ended May\u00a031, 2020 decreased $1.47 to $4.40 compared with diluted earnings per share of $5.87 for the prior-year period. This decrease reflects lower net income. Adjusted net income for the first nine months of fiscal 2020 was $234.5 million compared with $272.4 million in the prior-year period, a decrease of $37.9 million , or 13.9% . Adjusted diluted earnings per share for the nine months ended May\u00a031, 2020 decreased $0.92 , or 13.5% , to $5.91 compared with $6.83 for the prior-year period.\n29\n\nTable of Contents",
      "token_estimate": 2751
    },
    {
      "name": "Outlook",
      "section": "mda",
      "text": "We believe the execution of our strategy will provide attractive opportunities for profitable growth over the long term. Although we are aggressively managing our response to the recent COVID-19 pandemic, its impact on our full year fiscal 2020 results and beyond is uncertain.\u00a0We believe that the most significant elements of uncertainty are the intensity and duration of the impact on construction, renovation, and consumer spending as well as the ability of our sales channels, supply chain, manufacturing, and distribution to continue to operate with minimal disruption for the remainder of fiscal 2020 and beyond, all of which could negatively impact our financial position, results of operations, cash flows, and outlook.",
      "token_estimate": 181
    },
    {
      "name": "Critical Accounting Estimates",
      "section": "mda",
      "text": "Management\u2019s Discussion and Analysis of Financial Condition and Results of Operations addresses the financial condition and results of operations as reflected in our Consolidated Financial Statements , which have been prepared in accordance with U.S. GAAP. As discussed in the Description of Business and Basis of Presentation footnote of the Notes to Consolidated Financial Statements , the preparation of financial statements in conformity with U.S.\u00a0GAAP requires us to make estimates and assumptions that affect the reported amounts of assets and liabilities and disclosure of contingent assets and liabilities at the date of the financial statements and reported amounts of revenue and expense during the reporting period. On an ongoing basis, we evaluate our estimates and judgments, including those related to revenue recognition; inventory valuation; amortization and the recoverability of long-lived assets, including goodwill and intangible assets; share-based payment expense; medical, product warranty and recall, and other estimated liabilities; retirement benefits; and litigation. We base our estimates and judgments on our substantial historical experience and other relevant factors, the results of which form the basis for making judgments about the carrying values of assets and liabilities that are not readily apparent from other sources. Actual results could differ from those estimates. We discuss the development of accounting estimates with the Audit Committee of the Board.\nThere have been no material changes in our critical accounting estimates during the current period. For a detailed discussion of other significant accounting policies that may involve a higher degree of judgment, refer to our Form 10-K.",
      "token_estimate": 433
    },
    {
      "name": "Cautionary Statement Regarding Forward-Looking Information",
      "section": "mda",
      "text": "This filing contains forward-looking statements within the meaning of the federal securities laws. Statements made herein that may be considered forward-looking include statements incorporating terms such as \u201cexpects,\u201d \u201cbelieves,\u201d \u201cintends,\u201d \u201canticipates,\u201d and similar terms that relate to future events, performance, or results of the Company. In addition, the Company, or the executive officers on the Company\u2019s behalf, may from time to time make forward-looking statements in reports and other documents we file with the U.S. Securities and Exchange Commission or in connection with oral statements made to the press, current and potential investors, or others. Forward-looking statements include, without limitation: (a) our projections regarding financial performance, liquidity, capital structure, capital expenditures, investments, share repurchases, and dividends; (b) expectations about the impact of any changes in demand as well as volatility and uncertainty in general economic conditions; (c) our ability to execute and realize benefits from initiatives related to streamlining our operations, capitalize on growth opportunities, and introduce new lighting and building management solutions; (d) our estimate of our fiscal 2020 effective income tax rate, results of operations, and cash flows; (e) our estimate of future amortization expense; (f) our ability to achieve our long-term financial goals and measures and outperform the markets we serve; (g) the impact of changes in the political landscape and related policy changes, including monetary, regulatory, and trade policies; (h) our expectations related to mitigating efforts around recently imposed tariffs; (i) our expectations about the resolution of patent litigation, securities class action, trade compliance, and/or other legal matters; and (j) our expectations of the impact of the current COVID-19 pandemic. You are cautioned not to place undue reliance on any forward-looking statements, which speak only as of the date of this quarterly report. Except as required by law, we undertake no obligation to publicly update or release any revisions to these forward-looking statements to reflect any events or circumstances after the date of this quarterly report or to reflect the occurrence of unanticipated events. Our forward-looking statements are subject to certain risks and uncertainties that could cause actual results to differ materially from our historical experience and management\u2019s present expectations or projections. These risks and uncertainties that could cause our actual results to differ materially from those expressed in our forward-looking statements are discussed in Part II, Item 1a. Risk Factors below and Part I, Item 1a. Risk Factors of our Form\u00a010-K.\n30",
      "token_estimate": 690
    },
    {
      "name": "Risk Factors Overview",
      "section": "risk_factors",
      "text": "id=\"s376B83732F5358E2A64E6230F7F3A266\">\n\nItem 1a.Risk Factors",
      "token_estimate": 15
    },
    {
      "name": "The COVID-19 pandemic could have a material adverse effect our ability to operate, results of operations, financial condition, liquidity, and capital investments.",
      "section": "risk_factors",
      "text": "The World Health Organization has declared the COVID-19 outbreak a pandemic, and the virus continues to spread in areas where we operate and sell our products and services. The COVID-19 pandemic and similar issues in the future could have a material adverse effect on our ability to operate, results of operations, financial condition, liquidity, and capital investments. Several public health organizations have recommended, and some local governments have implemented, certain measures to slow and limit the transmission of the virus, including shelter in place and social distancing ordinances. The pandemic and such preventive measures, or others required or that we may voluntarily put in place, may have a material adverse effect on our business for an indefinite period of time, such as the potential shut down of certain locations; decreased employee availability; increased claims or other expenses; potential border closures; disruptions to the businesses of our channel partners; and others. Our suppliers and customers have also faced these and other challenges, which has led to a disruption in our supply chain for certain components as well as decreased construction and renovation spending and consumer demand for our products and services. These disruptions and challenges may continue for an indefinite period of time and may also materially affect our future access to our sources of liquidity, particularly our cash flows from operations, financial condition, capitalization, and capital investments. Although these disruptions may continue to occur, the long-term economic impact and near-term financial impacts of the COVID-19 pandemic, including but not limited to, possible impairment, restructuring, and other charges, cannot be reliably quantified or estimated at this time due to the uncertainty of future developments.\nOther than the item listed above, there have been no material changes in our risk factors from those disclosed in Part I, Item 1a. Risk Factors of our Form 10-K.\n\nItem 5.Other Information",
      "token_estimate": 508
    },
    {
      "name": "Declaration of Dividend",
      "section": "risk_factors",
      "text": "On June\u00a025, 2020 , the the Board of Directors (the \u201cBoard\u201d) declared a quarterly dividend of $0.13 per share. The dividend is payable on August\u00a03, 2020 to stockholders of record on July\u00a017, 2020 .\nExhibits are listed on the Index to Exhibits .\n33\n\nTable of Contents\nINDEX TO EXHIBITS\nEXHIBIT 3 (a) Restated Certificate of Incorporation of Acuity Brands, Inc. (formerly Acuity Brands Holdings, Inc.), dated as of September\u00a026, 2007. \u00a0 Reference is made to Exhibit 3.1 of registrant's Form 8-K as filed with the Commission on September 26, 2007, which is incorporated herein by reference. \u00a0 (b) Certificate of Amendment of Restated Certification of Incorporation of Acuity Brands, Inc. (formerly Acuity Brands Holdings, Inc.), dated as of September\u00a026, 2007. \u00a0 Reference is made to Exhibit 3.2 of registrant's Form 8-K as filed with the Commission on September 26, 2007, which is incorporated herein by reference. \u00a0 (c) Certificate of Amendment to the Restated Certificate of Incorporation of Acuity Brands, Inc., dated as of January 6, 2017. \u00a0 Reference is made to Exhibit 3.C of registrant's Form 10-Q as filed with the Commission on January 9, 2017, which is incorporated herein by reference. \u00a0 (d) Amended and Restated Bylaws of Acuity Brands, Inc., dated as of January 6, 2017. \u00a0 Reference is made to Exhibit 3.D of registrant's Form 10-Q as filed with the Commission on January 9, 2017, which is incorporated herein by reference. EXHIBIT 31 (a) Certification of the Chief Executive Officer of the Company pursuant to Section 302 of the Sarbanes-Oxley Act of 2002. \u00a0 Filed with the Commission as part of this Form 10-Q. \u00a0 (b) Certification of the Chief Financial Officer of the Company pursuant to Section 302 of the Sarbanes-Oxley Act of 2002. \u00a0 Filed with the Commission as part of this Form 10-Q. EXHIBIT 32 (a) Certification of the Chief Executive Officer of the Company pursuant to 18 U.S.C. Section 1350, as adopted pursuant to Section 906 of the Sarbanes-Oxley Act of 2002. \u00a0 Filed with the Commission as part of this Form 10-Q. \u00a0 (b) Certification of the Chief Financial Officer of the Company pursuant to 18 U.S.C. Section 1350, as adopted pursuant to Section 906 of the Sarbanes-Oxley Act of 2002. \u00a0 Filed with the Commission as part of this Form 10-Q. EXHIBIT 101 .INS XBRL Instance Document \u00a0 The instance document does not appear in the Interactive Data File because its XBRL tags are embedded within the Inline XBRL document. \u00a0 .SCH XBRL Taxonomy Extension Schema Document. \u00a0 Filed with the Commission as part of this Form 10-Q. \u00a0 .CAL XBRL Taxonomy Extension Calculation Linkbase Document. \u00a0 Filed with the Commission as part of this Form 10-Q. \u00a0 .DEF XBRL Taxonomy Extension Definition Linkbase Document. \u00a0 Filed with the Commission as part of this Form 10-Q. \u00a0 .LAB XBRL Taxonomy Extension Label Linkbase Document. \u00a0 Filed with the Commission as part of this Form 10-Q. \u00a0 .PRE XBRL Taxonomy Extension Presentation Linkbase Document. \u00a0 Filed with the Commission as part of this Form 10-Q. EXHIBIT 104 \u00a0 Cover Page Interactive Data File (formatted as inline XBRL and contained in Exhibit 101) \u00a0 Filed with the Commission as part of this Form 10-Q\n34\n\nTable of Contents\nSIGNATURES\nPursuant to the requirements of the Securities Exchange Act of 1934, the registrant has duly caused this report to be signed on its behalf by the undersigned, thereunto duly authorized.\nACUITY BRANDS, INC.\nDate: June\u00a030, 2020 \u00a0 By: /S/\u00a0\u00a0NEIL M. ASHE \u00a0 \u00a0 \u00a0 \u00a0 NEIL M. ASHE PRESIDENT AND CHIEF EXECUTIVE OFFICER\nDate: June\u00a030, 2020 \u00a0 By: /S/\u00a0\u00a0KAREN J. HOLCOM \u00a0 \u00a0 \u00a0 \u00a0 KAREN J. HOLCOM SENIOR VICE PRESIDENT AND CHIEF FINANCIAL OFFICER (Principal Financial and Accounting Officer)\n35",
      "token_estimate": 918
    }
  ]
}